pycounts_vcm/__init__.py
pycounts_vcm/data/flatland.txt
pycounts_vcm/datasets.py
pycounts_vcm/plotting.py
pycounts_vcm/pycounts_vcm.py
pycounts_vcm-0.2.0.dist-info/LICENSE
pycounts_vcm-0.2.0.dist-info/WHEEL
pycounts_vcm-0.2.0.dist-info/METADATA
pycounts_vcm-0.2.0.dist-info/RECORD
